README.rst
setup.py
limited_ordered_set/__init__.py
limited_ordered_set.egg-info/PKG-INFO
limited_ordered_set.egg-info/SOURCES.txt
limited_ordered_set.egg-info/dependency_links.txt
limited_ordered_set.egg-info/requires.txt
limited_ordered_set.egg-info/top_level.txt