Metadata-Version: 1.1
Name: limited-ordered-set
Version: 0.1.0
Summary: Limited Ordered Set object. Data type for storing actions history lists.
Home-page: https://github.com/phpdude/limited-ordered-set
Author: Alexandr Shurigin
Author-email: alexandr.shurigin@gmail.com
License: BSD
Keywords: collection library type set list limited
Platform: UNKNOWN
Classifier: Intended Audience :: Information Technology
Classifier: Intended Audience :: Legal Industry
Classifier: License :: OSI Approved :: BSD License
Classifier: Natural Language :: English
Classifier: Operating System :: OS Independent
Classifier: Programming Language :: Python
Classifier: Topic :: Software Development :: Libraries
